magnum_cluster_api-0.35.0.dist-info/METADATA
magnum_cluster_api-0.35.0.dist-info/WHEEL
magnum_cluster_api-0.35.0.dist-info/entry_points.txt
magnum_cluster_api-0.35.0.dist-info/licenses/LICENSE
magnum_cluster_api/__init__.py
magnum_cluster_api/cache.py
magnum_cluster_api/charts/.gitkeep
magnum_cluster_api/charts/cilium/.helmignore
magnum_cluster_api/charts/cilium/Chart.yaml
magnum_cluster_api/charts/cilium/LICENSE
magnum_cluster_api/charts/cilium/README.md
magnum_cluster_api/charts/cilium/README.md.gotmpl
magnum_cluster_api/charts/cilium/files/agent/poststart-eni.bash
magnum_cluster_api/charts/cilium/files/cilium-agent/dashboards/cilium-dashboard.json
magnum_cluster_api/charts/cilium/files/cilium-envoy/configmap/bootstrap-config.json
magnum_cluster_api/charts/cilium/files/cilium-operator/dashboards/cilium-operator-dashboard.json
magnum_cluster_api/charts/cilium/files/hubble/dashboards/hubble-dashboard.json
magnum_cluster_api/charts/cilium/files/hubble/dashboards/hubble-dns-namespace.json
magnum_cluster_api/charts/cilium/files/hubble/dashboards/hubble-l7-http-metrics-by-workload.json
magnum_cluster_api/charts/cilium/files/hubble/dashboards/hubble-network-overview-namespace.json
magnum_cluster_api/charts/cilium/files/nodeinit/prestop.bash
magnum_cluster_api/charts/cilium/files/nodeinit/startup.bash
magnum_cluster_api/charts/cilium/files/spire/init.bash
magnum_cluster_api/charts/cilium/files/spire/wait-for-spire.bash
magnum_cluster_api/charts/cilium/requirements.lock
magnum_cluster_api/charts/cilium/templates/NOTES.txt
magnum_cluster_api/charts/cilium/templates/_helpers.tpl
magnum_cluster_api/charts/cilium/templates/cilium-agent/clusterrole.yaml
magnum_cluster_api/charts/cilium/templates/cilium-agent/clusterrolebinding.yaml
magnum_cluster_api/charts/cilium/templates/cilium-agent/daemonset.yaml
magnum_cluster_api/charts/cilium/templates/cilium-agent/dashboards-configmap.yaml
magnum_cluster_api/charts/cilium/templates/cilium-agent/role.yaml
magnum_cluster_api/charts/cilium/templates/cilium-agent/rolebinding.yaml
magnum_cluster_api/charts/cilium/templates/cilium-agent/service.yaml
magnum_cluster_api/charts/cilium/templates/cilium-agent/serviceaccount.yaml
magnum_cluster_api-0.35.0.dist-info/RECORD
