Metadata-Version: 2.4
Name: magnum-cluster-api
Version: 0.35.0
Classifier: Development Status :: 5 - Production/Stable
Classifier: Environment :: OpenStack
Classifier: Intended Audience :: Information Technology
Classifier: Intended Audience :: System Administrators
Classifier: License :: OSI Approved :: Apache Software License
Classifier: Natural Language :: English
Classifier: Operating System :: POSIX :: Linux
Classifier: Programming Language :: Python :: 3.10
Classifier: Programming Language :: Python :: 3.11
Classifier: Programming Language :: Python :: 3.12
Classifier: Programming Language :: Python :: 3.13
Classifier: Programming Language :: Python :: Implementation :: CPython
Requires-Dist: certifi
Requires-Dist: click>=8.0.4
Requires-Dist: diskcache>=5.6.1
Requires-Dist: eventlet>=0.33.1
Requires-Dist: haproxyadmin>=0.2.4
Requires-Dist: kubernetes>=24.2.0
Requires-Dist: magnum>=15.0.0
Requires-Dist: oslo-concurrency>=4.5.0
Requires-Dist: oslo-config>=8.8.0
Requires-Dist: oslo-context>=4.1.0
Requires-Dist: oslo-log>=4.7.0
Requires-Dist: oslo-privsep>=2.7.0
Requires-Dist: oslo-service>=2.8.0
Requires-Dist: platformdirs>=2.4.0
Requires-Dist: pykube-ng
Requires-Dist: pyroute2>=0.3.4
Requires-Dist: python-heatclient
Requires-Dist: python-manilaclient>=3.3.2
Requires-Dist: requests>=2.27.1
Requires-Dist: semver>=2.0.0
Requires-Dist: sherlock>=0.4.1
Requires-Dist: shortuuid
License-File: LICENSE
Summary: Cluster API driver for Magnum
Author-email: Mohammed Naser <mnaser@vexxhost.com>
License-Expression: Apache-2.0
Requires-Python: >=3.10
